drf_relative/__init__.py
drf_relative/views.py
drf_relative-0.0.dist-info/LICENSE.md
drf_relative-0.0.dist-info/METADATA
drf_relative-0.0.dist-info/WHEEL
drf_relative-0.0.dist-info/top_level.txt
drf_relative-0.0.dist-info/RECORD
