Metadata-Version: 2.1
Name: drf-relative
Version: 0.0
Summary: Fast ways to handle model relations for CRUD.
Author: iamkorniichuk
Author-email: iamkorniichuk@gmail.com
Project-URL: Source, https://github.com/iamkorniichuk/drf-relative
Project-URL: Tracker, https://github.com/iamkorniichuk/drf-relative/issues
Classifier: Programming Language :: Python :: 3
Classifier: License :: OSI Approved :: MIT License
Classifier: Operating System :: OS Independent
Requires-Python: >=3.11
License-File: LICENSE.md
Requires-Dist: djangorestframework>=3.15.2
